ml_etl_package/__init__.py
ml_etl_package/extract.py
ml_etl_package/load.py
ml_etl_package/model.py
ml_etl_package/predict.py
ml_etl_package/transform.py
ml_etl_package-0.1.0.dist-info/METADATA
ml_etl_package-0.1.0.dist-info/WHEEL
ml_etl_package-0.1.0.dist-info/top_level.txt
ml_etl_package-0.1.0.dist-info/RECORD
