Metadata-Version: 2.4
Name: ml-etl-package
Version: 0.1.0
Summary: A simple ML pipeline package with ETL steps using scikit-learn
Author-email: Your Name <you@example.com>
Requires-Python: >=3.8
Requires-Dist: pandas
Requires-Dist: scikit-learn
Requires-Dist: joblib
